package org.andengine.b.b.a;

import java.util.ArrayList;
import org.andengine.b.b.c;

public class a
  implements c
{
  private final ArrayList a = new ArrayList();
  
  /* Error */
  public void a_(float paramFloat)
  {
    // Byte code:
    //   0: aload_0
    //   1: monitorenter
    //   2: aload_0
    //   3: getfield 17	org/andengine/b/b/a/a:a	Ljava/util/ArrayList;
    //   6: astore_3
    //   7: aload_3
    //   8: invokevirtual 23	java/util/ArrayList:size	()I
    //   11: istore 4
    //   13: iload 4
    //   15: iconst_1
    //   16: isub
    //   17: istore 5
    //   19: iload 5
    //   21: ifge +6 -> 27
    //   24: aload_0
    //   25: monitorexit
    //   26: return
    //   27: aload_3
    //   28: iload 5
    //   30: invokevirtual 27	java/util/ArrayList:remove	(I)Ljava/lang/Object;
    //   33: checkcast 29	java/lang/Runnable
    //   36: invokeinterface 32 1 0
    //   41: iinc 5 255
    //   44: goto -25 -> 19
    //   47: astore_2
    //   48: aload_0
    //   49: monitorexit
    //   50: aload_2
    //   51: athrow
    // Local variable table:
    //   start	length	slot	name	signature
    //   0	52	0	this	a
    //   0	52	1	paramFloat	float
    //   47	4	2	localObject	Object
    //   6	22	3	localArrayList	ArrayList
    //   11	6	4	i	int
    //   17	25	5	j	int
    // Exception table:
    //   from	to	target	type
    //   2	13	47	finally
    //   27	41	47	finally
  }
}


/* Location:           P:\Side\classes-dex2jar.jar
 * Qualified Name:     org.andengine.b.b.a.a
 * JD-Core Version:    0.7.0.1
 */